pystopwatch2/__init__.py
pystopwatch2/test.py
pystopwatch2/watch.py
pystopwatch2-0.1.1.dist-info/LICENSE
pystopwatch2-0.1.1.dist-info/METADATA
pystopwatch2-0.1.1.dist-info/WHEEL
pystopwatch2-0.1.1.dist-info/top_level.txt
pystopwatch2-0.1.1.dist-info/RECORD
