Metadata-Version: 2.1
Name: pystopwatch2
Version: 0.1.1
Summary: Multi-functional Stopwatch for Python
Home-page: https://github.com/ildoonet/pystopwatch2
License: MIT License
Platform: UNKNOWN
Requires-Dist: enum34
